Metadata-Version: 2.2
Name: relocal-adr
Version: 0.1.1
Summary: ADR: Real-Time and Robust 3D Place Recognition with Adaptive Data Reorganization and Geodesic-Constrained Plane Suppression
Keywords: pointcloud,lidar,autonomous driving,place recognition,3d vision,loop closure detection
Author-Email: HopeCollector <cmw0249@gmail.com>
License: MIT License
Classifier: Programming Language :: Python :: 3
Classifier: License :: OSI Approved :: MIT License
Classifier: Operating System :: POSIX :: Linux
Classifier: Intended Audience :: Science/Research
Classifier: Topic :: Scientific/Engineering :: Information Analysis
Classifier: Topic :: Software Development :: Libraries :: Python Modules
Project-URL: Homepage, https://github.com/HopeCollector/adr_code
Project-URL: Documentation, https://github.com/HopeCollector/adr_code#readme
Project-URL: Source, https://github.com/HopeCollector/adr_code
Requires-Python: >=3.8
